Workbook
Name prazo_anos: Ferramenta!$D$19
Name salario: Ferramenta!$D$13
Name perfil_selecionado: Ferramenta!$C$31
Name Aporte: Ferramenta!$D$18
Name patrimonio_acumulado: Ferramenta!$D$21
Name Rendimento_Carteira: Ferramenta!$D$14
Name taxa_mensal: Ferramenta!$D$20
Name valor_investir_mensal: Ferramenta!$C$32
Name sugestao_investimento: Ferramenta!$D$15

Sheet Ferramenta
B12: Configurações
B13: Salário | D13: 10000
B14: Rendimento Carteira | D14: 0.0089
B15: Sugestão de investimento (30%) | D15: =salario*30%*-1 -> -3000
B17: Investimento Mensal
B18: Quanto investir por mês? | D18: -1280
B19: Por quantos anos? | D19: 10
B20: Taxa de rendimento mensal | D20: 0.01079
B21: Patrimônio acumulado | D21: =FV(taxa_mensal,prazo_anos*12,Aporte) -> 311403.79
B22: Dividendos mensais | D22: =patrimonio_acumulado*Rendimento_Carteira -> 2771.4937
B24: Cenários | D24: Dividendo
B25: 2 | C25: =FV(taxa_mensal,B25*12,Aporte) -> 34851.363 | D25: =C25*Rendimento_Carteira -> 310.17713
B26: 5 | C26: =FV(taxa_mensal,B26*12,Aporte) -> 107234.45 | D26: =C26*Rendimento_Carteira -> 954.3866
B27: 10 | C27: =FV(taxa_mensal,B27*12,Aporte) -> 311403.79 | D27: =C27*Rendimento_Carteira -> 2771.4937
B28: 20 | C28: =FV(taxa_mensal,B28*12,Aporte) -> 1440254 | D28: =C28*Rendimento_Carteira -> 12818.26
B29: 30 | C29: =FV(taxa_mensal,B29*12,Aporte) -> 5532377.2 | D29: =C29*Rendimento_Carteira -> 49238.157
B31: Perfil | C31: Conservador
B32: Valor a ser investido por mês | C32: =D18 -> -1280
B34: TIPO DE FII | C34: Percentual sugerido | D34: Valores
B35: PAPEL | C35: =VLOOKUP(perfil_selecionado&"-"&B35,'Tabela de Apoio'!$A$3:$D$21,4,FALSE) -> 0.3 | D35: =valor_investir_mensal*C35*-1 -> 384
B36: TIJOLO | C36: =VLOOKUP(perfil_selecionado&"-"&B36,'Tabela de Apoio'!$A$3:$D$21,4,FALSE) -> 0.5 | D36: =valor_investir_mensal*C36*-1 -> 640
B37: HÍBRIDOS | C37: =VLOOKUP(perfil_selecionado&"-"&B37,'Tabela de Apoio'!$A$3:$D$21,4,FALSE) -> 0.1 | D37: =valor_investir_mensal*C37*-1 -> 128
B38: FOFs | C38: =VLOOKUP(perfil_selecionado&"-"&B38,'Tabela de Apoio'!$A$3:$D$21,4,FALSE) -> 0.1 | D38: =valor_investir_mensal*C38*-1 -> 128
B39: DESENVOLVIMENTO | C39: =VLOOKUP(perfil_selecionado&"-"&B39,'Tabela de Apoio'!$A$3:$D$21,4,FALSE) -> 0 | D39: =valor_investir_mensal*C39*-1 -> 0
B40: HOTELARIAS | C40: =VLOOKUP(perfil_selecionado&"-"&B40,'Tabela de Apoio'!$A$3:$D$21,4,FALSE) -> 0 | D40: =valor_investir_mensal*C40*-1 -> 0
B41: Total | D41: =SUM(D35:D40) -> 1280

Sheet Tabela de Apoio
A1: Alocação de FIIs por Perfil
A2: Diretrizes e percentuais recomendados por categoria de fundo imobiliário
A3: Chave | B3: Perfil | C3: TIPO DE FII | D3: % | G3: Chave de Busca | H3: % Alocado
A4: =B4&"-"&C4 -> Conservador-PAPEL | B4: Conservador | C4: PAPEL | D4: 0.3 | G4: Moderado-TIJOLO | H4: =VLOOKUP(G4,A3:D22,4,FALSE) -> 0.35
A5: =B5&"-"&C5 -> Conservador-TIJOLO | B5: Conservador | C5: TIJOLO | D5: 0.5
A6: =B6&"-"&C6 -> Conservador-HÍBRIDOS | B6: Conservador | C6: HÍBRIDOS | D6: 0.1
A7: =B7&"-"&C7 -> Conservador-FOFs | B7: Conservador | C7: FOFs | D7: 0.1
A8: =B8&"-"&C8 -> Conservador-DESENVOLVIMENTO | B8: Conservador | C8: DESENVOLVIMENTO | D8: 0
A9: =B9&"-"&C9 -> Conservador-HOTELARIAS | B9: Conservador | C9: HOTELARIAS | D9: 0
A10: =B10&"-"&C10 -> Moderado-PAPEL | B10: Moderado | C10: PAPEL | D10: 0.32
A11: =B11&"-"&C11 -> Moderado-TIJOLO | B11: Moderado | C11: TIJOLO | D11: 0.35
A12: =B12&"-"&C12 -> Moderado-HÍBRIDOS | B12: Moderado | C12: HÍBRIDOS | D12: 0.08
A13: =B13&"-"&C13 -> Moderado-FOFs | B13: Moderado | C13: FOFs | D13: 0.05
A14: =B14&"-"&C14 -> Moderado-DESENVOLVIMENTO | B14: Moderado | C14: DESENVOLVIMENTO | D14: 0.1
A15: =B15&"-"&C15 -> Moderado-HOTELARIAS | B15: Moderado | C15: HOTELARIAS | D15: 0.1
A16: =B16&"-"&C16 -> Agressivo-PAPEL | B16: Agressivo | C16: PAPEL | D16: 0.5
... A21: =B21&"-"&C21 -> Agressivo-HOTELARIAS | B21: Agressivo | C21: HOTELARIAS | D21: 0.1
